jneqsim/__init__.py
jneqsim/__init__.pyi
jneqsim/common/config.yaml
jneqsim/common/load_config.py
jneqsim/common/setup_logging.py
jneqsim/dependency_manager.py
jneqsim/jar_cache.py
jneqsim/jvm_service.py
jneqsim/neqsim/__init__.pyi
jneqsim/neqsim/api/__init__.pyi
jneqsim/neqsim/api/ioc/__init__.pyi
jneqsim/neqsim/blackoil/__init__.pyi
jneqsim/neqsim/blackoil/io/__init__.pyi
jneqsim/neqsim/chemicalreactions/__init__.pyi
jneqsim/neqsim/chemicalreactions/chemicalequilibrium/__init__.pyi
jneqsim/neqsim/chemicalreactions/chemicalreaction/__init__.pyi
jneqsim/neqsim/chemicalreactions/kinetics/__init__.pyi
jneqsim/neqsim/datapresentation/__init__.pyi
jneqsim/neqsim/datapresentation/filehandling/__init__.pyi
jneqsim/neqsim/datapresentation/jfreechart/__init__.pyi
jneqsim/neqsim/fluidmechanics/__init__.pyi
jneqsim/neqsim/fluidmechanics/flowleg/__init__.pyi
jneqsim/neqsim/fluidmechanics/flowleg/pipeleg/__init__.pyi
jneqsim/neqsim/fluidmechanics/flownode/__init__.pyi
jneqsim/neqsim/fluidmechanics/flownode/fluidboundary/__init__.pyi
jneqsim/neqsim/fluidmechanics/flownode/fluidboundary/heatmasstransfercalc/__init__.pyi
jneqsim/neqsim/fluidmechanics/flownode/fluidboundary/heatmasstransfercalc/equilibriumfluidboundary/__init__.pyi
jneqsim/neqsim/fluidmechanics/flownode/fluidboundary/heatmasstransfercalc/finitevolumeboundary/__init__.pyi
jneqsim/neqsim/fluidmechanics/flownode/fluidboundary/heatmasstransfercalc/finitevolumeboundary/fluidboundarynode/__init__.pyi
jneqsim/neqsim/fluidmechanics/flownode/fluidboundary/heatmasstransfercalc/finitevolumeboundary/fluidboundarynode/fluidboundarynonreactivenode/__init__.pyi
jneqsim/neqsim/fluidmechanics/flownode/fluidboundary/heatmasstransfercalc/finitevolumeboundary/fluidboundarynode/fluidboundaryreactivenode/__init__.pyi
jneqsim/neqsim/fluidmechanics/flownode/fluidboundary/heatmasstransfercalc/finitevolumeboundary/fluidboundarysolver/__init__.pyi
jneqsim-3.3.0.dist-info/METADATA
jneqsim-3.3.0.dist-info/WHEEL
jneqsim-3.3.0.dist-info/licenses/LICENSE
jneqsim-3.3.0.dist-info/RECORD
