Metadata-Version: 2.4
Name: jneqsim
Version: 3.3.0
Summary: Python bindings for the Java library NeqSim (via JPype), with python stubs
License: Apache-2.0
License-File: LICENSE
Keywords: neqsim
Author: Jørgen
Author-email: jenge@equinor.com
Maintainer: Mathias
Maintainer-email: maohe@equinor.com
Requires-Python: >=3.9,<4.0
Classifier: License :: OSI Approved :: Apache Software License
Classifier: Programming Language :: Python :: 3
Classifier: Programming Language :: Python :: 3.9
Classifier: Programming Language :: Python :: 3.10
Classifier: Programming Language :: Python :: 3.11
Classifier: Programming Language :: Python :: 3.12
Classifier: Programming Language :: Python :: 3.13
Classifier: Programming Language :: Python :: 3.14
Requires-Dist: JPype1 (>=1.5.0,<2.0.0)
Requires-Dist: PyYAML (>=6.0,<7.0)
Project-URL: Homepage, https://github.com/equinor/jneqsim
Project-URL: Repository, https://github.com/equinor/jneqsim
